{
  "version": "5",
  "dialect": "pg",
  "id": "90451b5c-50bb-4e59-8904-ba497fc14289",
  "prevId": "00000000-0000-0000-0000-000000000000",
  "tables": {
    "cartTable": {
      "name": "cartTable",
      "schema": "",
      "columns": {
        "cart_id": {
          "name": "cart_id",
          "type": "serial",
          "primaryKey": true,
          "notNull": true
        },
        "user_id": {
          "name": "user_id",
          "type": "varchar(255)",
          "primaryKey": false,
          "notNull": true
        },
        "product_name": {
          "name": "product_name",
          "type": "varchar(256)",
          "primaryKey": false,
          "notNull": true
        },
        "product_id": {
          "name": "product_id",
          "type": "varchar(255)",
          "primaryKey": false,
          "notNull": true
        },
        "product_type": {
          "name": "product_type",
          "type": "varchar(100)",
          "primaryKey": false,
          "notNull": true
        },
        "product_image_url": {
          "name": "product_image_url",
          "type": "text",
          "primaryKey": false,
          "notNull": true
        },
        "product_quantity": {
          "name": "product_quantity",
          "type": "integer",
          "primaryKey": false,
          "notNull": true
        },
        "product_price": {
          "name": "product_price",
          "type": "integer",
          "primaryKey": false,
          "notNull": true
        }
      },
      "indexes": {},
      "foreignKeys": {},
      "compositePrimaryKeys": {},
      "uniqueConstraints": {}
    }
  },
  "enums": {},
  "schemas": {},
  "_meta": {
    "schemas": {},
    "tables": {},
    "columns": {}
  }
}